localstorage/__init__.py
localstorage/localstorage.py
localstorage-0.1.0.dist-info/DESCRIPTION.rst
localstorage-0.1.0.dist-info/METADATA
localstorage-0.1.0.dist-info/RECORD
localstorage-0.1.0.dist-info/WHEEL
localstorage-0.1.0.dist-info/metadata.json
localstorage-0.1.0.dist-info/top_level.txt
