Metadata-Version: 1.1
Name: localstorage
Version: 0.1.0
Summary: Short description soon...
Home-page: https://github.com/sbneto/localstorage
Author: Samuel Barbosa
Author-email: samuel.m.b.neto@gmail.com
License: MIT license
Keywords: localstorage
Platform: UNKNOWN
Classifier: Development Status :: 2 - Pre-Alpha
Classifier: Intended Audience :: Developers
Classifier: License :: OSI Approved :: MIT License
Classifier: Natural Language :: English
Classifier: Programming Language :: Python :: 2
Classifier: Programming Language :: Python :: 2.7
Classifier: Programming Language :: Python :: 3
Classifier: Programming Language :: Python :: 3.4
Classifier: Programming Language :: Python :: 3.5
Classifier: Programming Language :: Python :: 3.6
Classifier: Programming Language :: Python :: 3.7
